cold_wax/__init__.py
cold_wax/data/__init__.py
cold_wax/data/utils.py
cold_wax/image/__init__.py
cold_wax/image/image.py
cold_wax/models/__init__.py
cold_wax/models/classifiers.py
cold_wax/signal/__init__.py
cold_wax/signal/signal.py
cold_wax-0.0.6.dist-info/LICENSE
cold_wax-0.0.6.dist-info/METADATA
cold_wax-0.0.6.dist-info/WHEEL
cold_wax-0.0.6.dist-info/top_level.txt
cold_wax-0.0.6.dist-info/RECORD
