Metadata-Version: 2.1
Name: cold-wax
Version: 0.0.6
Summary: Various python tools I use frequently.
Home-page: https://gitlab.com/__matt/cold-wax
Author: Mattia Colombo
Author-email: mattia.clmb@gmail.com
License: UNKNOWN
Project-URL: Bug Tracker, https://gitlab.com/__matt/cold-wax/-/issues
Platform: UNKNOWN
Classifier: Programming Language :: Python :: 3
Classifier: License :: OSI Approved :: MIT License
Classifier: Operating System :: OS Independent
Requires-Python: >=3.6
Requires-Dist: requests
Requires-Dist: numpy
Requires-Dist: scipy
Requires-Dist: opencv-contrib-python
Requires-Dist: soundfile
